datacontracts/__init__.py
datacontracts/column.py
datacontracts/contract.py
datacontracts/errors.py
datacontracts-0.1.5.dist-info/METADATA
datacontracts-0.1.5.dist-info/WHEEL
datacontracts-0.1.5.dist-info/top_level.txt
datacontracts-0.1.5.dist-info/RECORD
