Metadata-Version: 2.4
Name: datacontracts
Version: 0.1.5
Summary: datacontracts v0.1.3 lets you define business-friendly data rules and reports every invalid row with clear messages.
Author: M.Umer Farooq
License: MIT
Project-URL: Homepage, https://github.com/ben-slates/datacontracts
Project-URL: Repository, https://github.com/ben-slates/datacontracts
Project-URL: Issues, https://github.com/ben-slates/datacontracts/issues
Classifier: Programming Language :: Python :: 3
Classifier: Programming Language :: Python :: 3.9
Classifier: Programming Language :: Python :: 3.10
Classifier: Programming Language :: Python :: 3.11
Classifier: Programming Language :: Python :: 3.12
Classifier: Programming Language :: Python :: 3.13
Classifier: License :: OSI Approved :: MIT License
Requires-Python: >=3.9
Requires-Dist: pandas
